lrcs/__init__.py
lrcs-0.0.1.dev0.dist-info/COPYING
lrcs-0.0.1.dev0.dist-info/COPYING.lesser
lrcs-0.0.1.dev0.dist-info/LICENSE
lrcs-0.0.1.dev0.dist-info/METADATA
lrcs-0.0.1.dev0.dist-info/WHEEL
lrcs-0.0.1.dev0.dist-info/top_level.txt
lrcs-0.0.1.dev0.dist-info/RECORD
