Metadata-Version: 2.1
Name: lrcs
Version: 0.0.1.dev0
Summary: Soon
Author-email: ZAID <me@zaid.pro>
Classifier: Programming Language :: Python :: 3
Classifier: License :: OSI Approved :: MIT License
Classifier: Operating System :: OS Independent
Requires-Python: >=3.8
License-File: LICENSE
License-File: COPYING
License-File: COPYING.lesser
